demirbank/__init__.py
demirbank/errors.py
demirbank/messages.py
demirbank/models.py
demirbank/parsers.py
demirbank/utils.py
demirbank/views.py
demirbank/migrations/0001_initial.py
demirbank/migrations/0002_demirbankpayment_demirbank_card.py
demirbank/migrations/__init__.py
django_demirbank-1.0.27a1.dist-info/DESCRIPTION.rst
django_demirbank-1.0.27a1.dist-info/METADATA
django_demirbank-1.0.27a1.dist-info/metadata.json
django_demirbank-1.0.27a1.dist-info/RECORD
django_demirbank-1.0.27a1.dist-info/top_level.txt
django_demirbank-1.0.27a1.dist-info/WHEEL
