Metadata-Version: 2.0
Name: django-demirbank
Version: 1.0.27a1
Summary: DemirBank library for making payment using store type = 3d_Pay_Hosting and transaction type = Auth
Home-page: https://github.com/CyberLight/django-demirbank
Author: CyberLight
Author-email: cyberlight@live.ru
License: MIT
Keywords: 3d_pay_hosting payment demirbank
Platform: UNKNOWN
Classifier: Development Status :: 3 - Alpha
Classifier: Intended Audience :: Developers
Classifier: Topic :: Office/Business :: Financial
Classifier: Operating System :: OS Independent
Classifier: Environment :: Web Environment
Classifier: Framework :: Django :: 1.7
Classifier: Framework :: Django :: 1.8
Classifier: License :: OSI Approved :: MIT License
Classifier: Programming Language :: Python :: 2
Classifier: Programming Language :: Python :: 2.6
Classifier: Programming Language :: Python :: 2.7
Classifier: Programming Language :: Python :: 3
Classifier: Programming Language :: Python :: 3.2
Classifier: Programming Language :: Python :: 3.3
Classifier: Programming Language :: Python :: 3.4
Requires-Dist: django (>=1.7,<1.9)
Provides-Extra: dev
Requires-Dist: wheel; extra == 'dev'
Requires-Dist: twine; extra == 'dev'
